Workbook

Sheet Project Plan
A1: 3B Michimap — SAP S/4HANA Brownfield Implementation Plan
A2: Start Date: 21 Mar 2026 | Total Duration: 24 weeks
A3: Phase | B3: Activity | C3: Responsible | D3: Discover | F3: Prepare | I3: Explore | M3: Realize - Develop | S3: Realize - UAT | V3: Deploy | X3: Run
A4: Week # | D4: W1 21 Mar | E4: W2 28 Mar | F4: W3 04 Apr | G4: W4 11 Apr | H4: W5 18 Apr | I4: W6 25 Apr | J4: W7 02 May | K4: W8 09 May | L4: W9 16 May | M4: W10 23 May | N4: W11 30 May | O4: W12 06 Jun | P4: W13 13 Jun | Q4: W14 20 Jun | R4: W15 27 Jun | S4: W16 04 Jul | T4: W17 11 Jul | U4: W18 18 Jul | V4: W19 25 Jul | W4: W20 01 Aug | X4: W21 08 Aug | Y4: W22 15 Aug | Z4: W23 22 Aug | AA4: W24 29 Aug
A5: Discover | B5: Run SAP Readiness Check 2.0 and review results (Simplification Items, Add-ons, Business Functions, Fiori Apps, Custom Code, Sizing) | C5: Project Manager, Technical Consultant, Basis Administrator, Functional Consultant
A6: Discover | B6: Execute SAP Transformation Navigator assessment and define target architecture (S/4HANA edition, deployment, FES embedded vs hub) | C6: Project Manager, Technical Consultant, Infrastructure Engineer, Customer Business Owner
A7: Discover | B7: Perform Custom Code analysis with ABAP Test Cockpit (ATC) incl. S/4HANA checks and baseline remediation approach | C7: Technical Consultant, Functional Consultant
A8: Discover | B8: High-level process impact assessment using Simplification Item Catalog and business impact log | C8: Functional Consultant, Customer Business Owner, Project Manager
A9: Discover | B9: Initial system landscape and downtime strategy assessment (DMO, ZDO options, SUM/DMO approach selection) | C9: Basis Administrator, Technical Consultant, Infrastructure Engineer, Project Manager
A10: Discover | B10: Create project charter and initial project plan in SAP Cloud ALM (scope, milestones, governance, Q-Gates) | C10: Project Manager, Customer Business Owner
A11: Prepare | B11: Set up SAP Cloud ALM for Implementation: project creation, team assignments, task plan import, governance setup | C11: Project Manager, Technical Consultant
A12: Prepare | B12: Define system landscape and transport strategy (DEV/QAS/PRD, ChaRM/CTS, retrofit approach for conversion) | C12: Project Manager, Basis Administrator, Technical Consultant
A13: Prepare | B13: Provision S/4HANA sandbox (copy/refresh from ECC) and prepare conversion toolchain prerequisites (SUM/DMO, SP levels) | C13: Basis Administrator, Infrastructure Engineer, Technical Consultant
A14: Prepare | B14: Set up SAP Fiori infrastructure and initial launchpad concept (roles, catalogs, groups/spaces/pages) | C14: Security Consultant, Basis Administrator, Technical Consultant
A15: Prepare | B15: Establish Test Management approach in SAP Cloud ALM (test strategy, test types, defect workflow, reporting) | C15: Project Manager, Functional Consultant, Technical Consultant
A16: Prepare | B16: Define cutover strategy and high-level conversion runbook (mock conversions, dress rehearsal plan, freeze windows) | C16: Project Manager, Basis Administrator, Functional Consultant
... A59: Run | B59: Project closure in SAP Cloud ALM: lessons learned, final status report, and backlog transition to continuous improvement | C59: Project Manager, Customer Business Owner, Functional Consultant, Technical Consultant

Sheet Effort Estimation
A1: 3B Michimap — Effort Estimation | Brownfield | Start: 21 Mar 2026
A2: Fill in effort (days) per phase per role. Rate, Total Days and Total Cost calculate automatically.
F3: Discover | G3: Prepare | H3: Explore | I3: Realize - Develop | J3: Realize - UAT | K3: Deploy | L3: Run
A4: # | B4: Role | C4: Onsite / Offshore | D4: Level | E4: Rate (USD/day) | F4: Discover (2w) | G4: Prepare (3w) | H4: Explore (4w) | I4: Realize - Develop (6w) | J4: Realize - UAT (3w) | K4: Deploy (2w) | L4: Run (4w) | M4: Total Days | N4: Total Cost (USD)
A5: 1 | B5: Project Manager | C5: Onsite | D5: Senior | E5: 1200 | M5: =SUM(F5,G5,H5,I5,J5,K5,L5) -> 0 | N5: =E5*M5 -> 0
A6: 2 | B6: Programme Manager | C6: Onsite | D6: Principal Architect | E6: 1500 | M6: =SUM(F6,G6,H6,I6,J6,K6,L6) -> 0 | N6: =E6*M6 -> 0
A7: 3 | B7: Solution Architect | C7: Onsite | D7: Solution Architect | E7: 1400 | M7: =SUM(F7,G7,H7,I7,J7,K7,L7) -> 0 | N7: =E7*M7 -> 0
A8: 4 | B8: Functional Consultant – Finance | C8: Offshore | D8: Senior | E8: 900 | M8: =SUM(F8,G8,H8,I8,J8,K8,L8) -> 0 | N8: =E8*M8 -> 0
A9: 5 | B9: Functional Consultant – Finance | C9: Offshore | D9: Junior | E9: 600 | M9: =SUM(F9,G9,H9,I9,J9,K9,L9) -> 0 | N9: =E9*M9 -> 0
A10: 6 | B10: Functional Consultant – MM/SD | C10: Offshore | D10: Senior | E10: 900 | M10: =SUM(F10,G10,H10,I10,J10,K10,L10) -> 0 | N10: =E10*M10 -> 0
A11: 7 | B11: Functional Consultant – MM/SD | C11: Offshore | D11: Junior | E11: 600 | M11: =SUM(F11,G11,H11,I11,J11,K11,L11) -> 0 | N11: =E11*M11 -> 0
A12: 8 | B12: Functional Consultant – PP/QM | C12: Offshore | D12: Senior | E12: 850 | M12: =SUM(F12,G12,H12,I12,J12,K12,L12) -> 0 | N12: =E12*M12 -> 0
A13: 9 | B13: Technical Consultant – ABAP | C13: Offshore | D13: Senior | E13: 800 | M13: =SUM(F13,G13,H13,I13,J13,K13,L13) -> 0 | N13: =E13*M13 -> 0
A14: 10 | B14: Technical Consultant – ABAP | C14: Offshore | D14: Junior | E14: 550 | M14: =SUM(F14,G14,H14,I14,J14,K14,L14) -> 0 | N14: =E14*M14 -> 0
A15: 11 | B15: Technical Consultant – Integration | C15: Offshore | D15: Senior | E15: 850 | M15: =SUM(F15,G15,H15,I15,J15,K15,L15) -> 0 | N15: =E15*M15 -> 0
A16: 12 | B16: Basis Administrator | C16: Offshore | D16: Senior | E16: 750 | M16: =SUM(F16,G16,H16,I16,J16,K16,L16) -> 0 | N16: =E16*M16 -> 0
... A22: 18 | B22: Infrastructure Engineer | C22: Offshore | D22: Senior | E22: 700 | M22: =SUM(F22,G22,H22,I22,J22,K22,L22) -> 0 | N22: =E22*M22 -> 0
E24: =AVERAGE(E5:E22) -> 0 | F24: =SUM(F5:F22) -> 0 | G24: =SUM(G5:G22) -> 0 | H24: =SUM(H5:H22) -> 0 | I24: =SUM(I5:I22) -> 0 | J24: =SUM(J5:J22) -> 0 | K24: =SUM(K5:K22) -> 0 | L24: =SUM(L5:L22) -> 0 | M24: =SUM(M5:M22) -> 0 | N24: =SUM(N5:N22) -> 0

Sheet Summary
A1: 3B Michimap — Effort Summary by Level | Brownfield
A2: Automatically summarised from Effort Estimation sheet. Fill in effort days there first.
B3: Discover | C3: Prepare | D3: Explore | E3: Realize - Develop | F3: Realize - UAT | G3: Deploy | H3: Run
A4: Level | B4: Discover | C4: Prepare | D4: Explore | E4: Realize - Develop | F4: Realize - UAT | G4: Deploy | H4: Run | I4: Total Days | J4: Total Cost (USD)
A5: Junior | B5: =SUMIF('Effort Estimation'!D5:D22,"Junior",'Effort Estimation'!F5:F22) -> 0 | C5: =SUMIF('Effort Estimation'!D5:D22,"Junior",'Effort Estimation'!G5:G22) -> 0 | D5: =SUMIF('Effort Estimation'!D5:D22,"Junior",'Effort Estimation'!H5:H22) -> 0 | E5: =SUMIF('Effort Estimation'!D5:D22,"Junior",'Effort Estimation'!I5:I22) -> 0 | F5: =SUMIF('Effort Estimation'!D5:D22,"Junior",'Effort Estimation'!J5:J22) -> 0 | G5: =SUMIF('Effort Estimation'!D5:D22,"Junior",'Effort Estimation'!K5:K22) -> 0 | H5: =SUMIF('Effort Estimation'!D5:D22,"Junior",'Effort Estimation'!L5:L22) -> 0 | I5: =SUMIF('Effort Estimation'!D5:D22,"Junior",'Effort Estimation'!M5:M22) -> 0 | J5: =SUMIF('Effort Estimation'!D5:D22,"Junior",'Effort Estimation'!N5:N22) -> 0
A6: Senior | B6: =SUMIF('Effort Estimation'!D5:D22,"Senior",'Effort Estimation'!F5:F22) -> 0 | C6: =SUMIF('Effort Estimation'!D5:D22,"Senior",'Effort Estimation'!G5:G22) -> 0 | D6: =SUMIF('Effort Estimation'!D5:D22,"Senior",'Effort Estimation'!H5:H22) -> 0 | E6: =SUMIF('Effort Estimation'!D5:D22,"Senior",'Effort Estimation'!I5:I22) -> 0 | F6: =SUMIF('Effort Estimation'!D5:D22,"Senior",'Effort Estimation'!J5:J22) -> 0 | G6: =SUMIF('Effort Estimation'!D5:D22,"Senior",'Effort Estimation'!K5:K22) -> 0 | H6: =SUMIF('Effort Estimation'!D5:D22,"Senior",'Effort Estimation'!L5:L22) -> 0 | I6: =SUMIF('Effort Estimation'!D5:D22,"Senior",'Effort Estimation'!M5:M22) -> 0 | J6: =SUMIF('Effort Estimation'!D5:D22,"Senior",'Effort Estimation'!N5:N22) -> 0
A7: Solution Architect | B7: =SUMIF('Effort Estimation'!D5:D22,"Solution Architect",'Effort Estimation'!F5:F22) -> 0 | C7: =SUMIF('Effort Estimation'!D5:D22,"Solution Architect",'Effort Estimation'!G5:G22) -> 0 | D7: =SUMIF('Effort Estimation'!D5:D22,"Solution Architect",'Effort Estimation'!H5:H22) -> 0 | E7: =SUMIF('Effort Estimation'!D5:D22,"Solution Architect",'Effort Estimation'!I5:I22) -> 0 | F7: =SUMIF('Effort Estimation'!D5:D22,"Solution Architect",'Effort Estimation'!J5:J22) -> 0 | G7: =SUMIF('Effort Estimation'!D5:D22,"Solution Architect",'Effort Estimation'!K5:K22) -> 0 | H7: =SUMIF('Effort Estimation'!D5:D22,"Solution Architect",'Effort Estimation'!L5:L22) -> 0 | I7: =SUMIF('Effort Estimation'!D5:D22,"Solution Architect",'Effort Estimation'!M5:M22) -> 0 | J7: =SUMIF('Effort Estimation'!D5:D22,"Solution Architect",'Effort Estimation'!N5:N22) -> 0
A8: Principal Architect | B8: =SUMIF('Effort Estimation'!D5:D22,"Principal Architect",'Effort Estimation'!F5:F22) -> 0 | C8: =SUMIF('Effort Estimation'!D5:D22,"Principal Architect",'Effort Estimation'!G5:G22) -> 0 | D8: =SUMIF('Effort Estimation'!D5:D22,"Principal Architect",'Effort Estimation'!H5:H22) -> 0 | E8: =SUMIF('Effort Estimation'!D5:D22,"Principal Architect",'Effort Estimation'!I5:I22) -> 0 | F8: =SUMIF('Effort Estimation'!D5:D22,"Principal Architect",'Effort Estimation'!J5:J22) -> 0 | G8: =SUMIF('Effort Estimation'!D5:D22,"Principal Architect",'Effort Estimation'!K5:K22) -> 0 | H8: =SUMIF('Effort Estimation'!D5:D22,"Principal Architect",'Effort Estimation'!L5:L22) -> 0 | I8: =SUMIF('Effort Estimation'!D5:D22,"Principal Architect",'Effort Estimation'!M5:M22) -> 0 | J8: =SUMIF('Effort Estimation'!D5:D22,"Principal Architect",'Effort Estimation'!N5:N22) -> 0
A9: Project Manager | B9: =SUMIF('Effort Estimation'!D5:D22,"Project Manager",'Effort Estimation'!F5:F22) -> 0 | C9: =SUMIF('Effort Estimation'!D5:D22,"Project Manager",'Effort Estimation'!G5:G22) -> 0 | D9: =SUMIF('Effort Estimation'!D5:D22,"Project Manager",'Effort Estimation'!H5:H22) -> 0 | E9: =SUMIF('Effort Estimation'!D5:D22,"Project Manager",'Effort Estimation'!I5:I22) -> 0 | F9: =SUMIF('Effort Estimation'!D5:D22,"Project Manager",'Effort Estimation'!J5:J22) -> 0 | G9: =SUMIF('Effort Estimation'!D5:D22,"Project Manager",'Effort Estimation'!K5:K22) -> 0 | H9: =SUMIF('Effort Estimation'!D5:D22,"Project Manager",'Effort Estimation'!L5:L22) -> 0 | I9: =SUMIF('Effort Estimation'!D5:D22,"Project Manager",'Effort Estimation'!M5:M22) -> 0 | J9: =SUMIF('Effort Estimation'!D5:D22,"Project Manager",'Effort Estimation'!N5:N22) -> 0
A11: GRAND TOTAL | B11: =SUM(B5:B9) -> 0 | C11: =SUM(C5:C9) -> 0 | D11: =SUM(D5:D9) -> 0 | E11: =SUM(E5:E9) -> 0 | F11: =SUM(F5:F9) -> 0 | G11: =SUM(G5:G9) -> 0 | H11: =SUM(H5:H9) -> 0 | I11: =SUM(I5:I9) -> 0 | J11: =SUM(J5:J9) -> 0
A13: Onsite vs. Offshore Breakdown
A14: Onsite | B14: (see Effort Estimation sheet for per-phase detail) | I14: =SUMIF('Effort Estimation'!C5:C22,"Onsite",'Effort Estimation'!M5:M22) -> 0 | J14: =SUMIF('Effort Estimation'!C5:C22,"Onsite",'Effort Estimation'!N5:N22) -> 0
A15: Offshore | B15: (see Effort Estimation sheet for per-phase detail) | I15: =SUMIF('Effort Estimation'!C5:C22,"Offshore",'Effort Estimation'!M5:M22) -> 0 | J15: =SUMIF('Effort Estimation'!C5:C22,"Offshore",'Effort Estimation'!N5:N22) -> 0
